branchunit.sv
module branchunit (
    input logic [31:0] rs1,
    input logic [31:0] rs2,
    input logic [4:0] BrOp,
    output logic NextPcSrc
);

  always @* begin
    if (BrOp[4] == 1) NextPcSrc <= 1;
    else if (BrOp[4] == 0 && BrOp[3] == 0) NextPcSrc <= 0;
    else if (BrOp[4] == 0 && BrOp[3] == 1) if (BrOp[2:0] == 3'b000) NextPcSrc <= rs1 == rs2;
    if (BrOp[2:0] == 3'b001) NextPcSrc <= rs1 != rs2;
    if (BrOp[2:0] == 3'b100) NextPcSrc <= signed'(rs1) < signed'(rs2);
    if (BrOp[2:0] == 3'b101) NextPcSrc <= signed'(rs1) >= signed'(rs2);
    if (BrOp[2:0] == 3'b110) NextPcSrc <= rs1 < rs2;
    if (BrOp[2:0] == 3'b111) NextPcSrc <= rs1 >= rs2;
  end

endmodule

immunit.sv
module immunit (
    input  logic [24:0] ImmInput,
    input  logic [ 2:0] ImmSrc,
    output logic [31:0] ImmExt
);

  always @* begin
    case (ImmSrc)
      3'b000:  ImmExt = {{20{ImmInput[24]}}, ImmInput[24:13]};
      3'b001:  ImmExt = {{20{ImmInput[24]}}, ImmInput[24:18], ImmInput[4:0]};
      3'b101:  ImmExt = {{20{ImmInput[24]}}, ImmInput[0], ImmInput[23:18], ImmInput[4:1], 1'b0};
      3'b010:  ImmExt = {ImmInput[24:5], {12{1'b0}}};
      3'b110:  ImmExt = {{12{ImmInput[24]}}, ImmInput[12:5], ImmInput[13], ImmInput[23:14], 1'b0};
      default: ImmExt = 0;
    endcase
  end
endmodule

datamemory.sv
module datamemory (
    input logic [31:0] Address,
    input logic [31:0] DataWr,
    input logic DMWr,
    input logic [2:0] DMCtrl,
    output logic [31:0] DataRd
);
  logic [7:0] memory[1023:0];

  always @* begin
    case (DMCtrl)
      3'b000:  DataRd <= {{24{memory[Address][7]}}, memory[Address]};
      3'b001:  DataRd <= {{16{memory[Address+1][7]}}, memory[Address+1], memory[Address]};
      3'b010:  DataRd <= {memory[Address+3], memory[Address+2], memory[Address+1], memory[Address]};
      3'b100:  DataRd <= {{24{1'b0}}, memory[Address]};
      3'b101:  DataRd <= {{16{1'b0}}, memory[Address+1], memory[Address]};
      default: DataRd <= 0;
    endcase

    if (DMWr)
      #1
      if (DMCtrl == 3'b000) memory[Address] <= DataWr[7:0];
      else if (DMCtrl == 3'b001) begin
        memory[Address]   <= DataWr[7:0];
        memory[Address+1] <= DataWr[15:8];
      end else if (DMCtrl == 3'b010) begin
        memory[Address]   <= DataWr[7:0];
        memory[Address+1] <= DataWr[15:8];
        memory[Address+2] <= DataWr[23:16];
        memory[Address+3] <= DataWr[31:24];
      end
  end

endmodule

alu.sv
// Code your design here
module alu (
    input  logic [31:0] A,
    input  logic [31:0] B,
    input  logic [ 3:0] ALUOp,
    output logic [31:0] S
);
  always @(A, B, ALUOp) begin
    case (ALUOp)
      4'b0000: S = A + B;
      4'b1000: S = A - B;
      4'b0010: S = (signed'(A) < signed'(B));
      4'b0011: S = A < B;
      4'b0001: S = A << B[4:0];
      4'b0100: S = A ^ B;
      4'b0101: S = A >> B[4:0];
      4'b1101: S = signed'(A) >>> B[4:0];
      4'b0110: S = A | B;
      4'b0111: S = A & B;
      default: S = 0;
    endcase
  end
endmodule

registerunit.sv
module registerunit (
    input  logic        clk,       // Clock input
    input  logic [ 4:0] rs1,
    rs2,  // Inputs to select registers
    input  logic [ 4:0] rd,        // Input to select register for writing
    input  logic        RuWr,      // Write enable signal
    input  logic [31:0] RuWrData,  // Data to be written to the selected register
    output logic [31:0] ru1,
    ru2  // Outputs from selected registers
);

  // Define 32 registers each of 32 bits
  logic [31:0] registers[0:31];
  // Wire up ru1 and ru2 outputs
  assign ru1 = registers[rs1];
  assign ru2 = registers[rs2];

  integer i;
  integer j;
  initial begin
    for (i = 0; i <= 32; i = i + 1) for (j = 0; j <= 32; j = j + 1) registers[i][j] = 0;
    registers[2] = 32'd512;
  end

  always_ff @(negedge clk) begin
    if (RuWr && rd != 0) registers[rd] <= RuWrData;
  end

endmodule

controlunit.sv
module controlunit (
    input logic [6:0] OpCode,
    input logic [2:0] Funct3,
    input logic [6:0] Funct7,
    output logic RUWr,
    output logic [3:0] ALUOp,
    output logic [2:0] ImmSrc,
    output logic ALUASrc,
    output logic ALUBSrc,
    output logic DMWr,
    output logic [2:0] DMCtrl,
    output logic [4:0] BrOp,
    output logic [1:0] RUDataWrSrc
);
  assign RUWr = OpCode[5:2] != 4'b1000;

  always @* begin
    if (OpCode == 7'b0010011)
      if (Funct3 == 3'b001 || Funct3 == 3'b101)
        ALUOp <= {Funct7[5], Funct3[2], Funct3[1], Funct3[0]};
      else
        ALUOp <= {1'b0, Funct3};
    else if (OpCode == 7'b0110011) ALUOp <= {Funct7[5], Funct3[2], Funct3[1], Funct3[0]};
    else if ((OpCode == 7'b0110111) || (OpCode == 7'b0010111)) ALUOp <= 4'b0111;
    else ALUOp <= 4'b0000;
  end

  assign ImmSrc = {
    OpCode[3] + (OpCode[6] * (~OpCode[2])),
    OpCode[3] + ((~OpCode[6]) * OpCode[2]),
    (OpCode[5] * (~OpCode[2]))
  };

  assign ALUASrc = OpCode[6] && OpCode != 7'b1100111;
  assign ALUBSrc = OpCode != 7'b0110011;
  assign DMWr = OpCode == 7'b0100011;
  assign DMCtrl = Funct3;
  assign BrOp = {~OpCode[4] * OpCode[2], OpCode[6], Funct3[2], Funct3[1], Funct3[0]};
  assign RUDataWrSrc = {OpCode[6], ((~OpCode[6]) * (~OpCode[4]))};
endmodule

instmemory.sv
module instmemory (
    input  logic [31:0] address,
    output logic [31:0] instruction
);
  logic [7:0] memory[0:1023];
  assign instruction = { memory[address], memory[address+1], memory[address+2], memory[address+3] };

  initial begin
    $readmemh("all_instructions.mem", memory);
  end
endmodule

pc.sv
module pc (
    input logic clk,
    input logic [31:0] pc_input,
    output logic [31:0] pc_output
);

  always_ff @(posedge clk) begin
    pc_output <= pc_input;
  end
endmodule

mono.sv
module mono (
    input logic clk
);
  logic [31:0] PcOutput;  // PC OUTPUT
  logic [31:0] PcPlus4;  // PC ADDED 4
  logic [31:0] BuPp4Mux;  // BRANCH UNIT and PC ADDED 4 mux
  logic [31:0] inst;  // INSTRUCTION MEMORY OUTPUT
  logic [31:0] RUDataMux;  // DATA MEMORY, ALU and PC ADDED 4 mux
  logic [31:0] RU1;  // REGISTER UNIT OUTPUT 1
  logic [31:0] RU2;  // REGISTER UNIT OUTPUT 2
  logic [31:0] ALUAMux;  // RU1 and PC mux
  logic [31:0] ALUBMux;  // RU2 and IMM GEN mux
  logic [31:0] ALURes;  // ALU OUTPUT
  logic [31:0] DataRd;  // DATA MEMORY OUTPUT
  logic [31:0] ImmExt;  // IMMEDIATE EXTENDED
  logic NextPcSrc;  // BRANCH UNIT OUTPUT

  /*    CONTROL UNIT    */
  logic RUWr;
  logic [3:0] ALUOp;
  logic [2:0] ImmSrc;
  logic ALUASrc;
  logic ALUBSrc;
  logic DMWr;
  logic [2:0] DMCtrl;
  logic [4:0] BrOp;
  logic [1:0] RUDataWrSrc;

  pc mpc (
      .clk(clk),
      .pc_input(BuPp4Mux),
      .pc_output(PcOutput)
  );

  instmemory minstmemory (
      .address(PcOutput),
      .instruction(inst)
  );

  controlunit mcontrolunit (
      .OpCode(inst[6:0]),
      .Funct3(inst[14:12]),
      .Funct7(inst[31:25]),
      .RUWr(RUWr),
      .ALUOp(ALUOp),
      .ImmSrc(ImmSrc),
      .ALUASrc(ALUASrc),
      .ALUBSrc(ALUBSrc),
      .DMWr(DMWr),
      .DMCtrl(DMCtrl),
      .BrOp(BrOp),
      .RUDataWrSrc(RUDataWrSrc)
  );

  registerunit mregisterunit (
      .clk(clk),
      .rs1(inst[19:15]),
      .rs2(inst[24:20]),
      .rd(inst[11:7]),
      .RuWr(RUWr),
      .RuWrData(RUDataMux),
      .ru1(RU1),
      .ru2(RU2)
  );

  alu malu (
      .A(ALUAMux),
      .B(ALUBMux),
      .ALUOp(ALUOp),
      .S(ALURes)
  );

  datamemory mdatamemory (
      .Address(ALURes),
      .DataWr(RU2),
      .DMWr(DMWr),
      .DMCtrl(DMCtrl),
      .DataRd(DataRd)
  );

  immunit mimmunit (
      .ImmInput(inst[31:7]),
      .ImmSrc  (ImmSrc),
      .ImmExt  (ImmExt)
  );

  branchunit mbranchunit (
      .rs1(RU2),
      .rs2(RU1),
      .BrOp(BrOp),
      .NextPcSrc(NextPcSrc)
  );

  always @* begin
    PcPlus4 <= PcOutput + 4;

    if (NextPcSrc) BuPp4Mux <= ALURes;
    else BuPp4Mux <= PcPlus4;

    if (ALUASrc) ALUAMux <= PcOutput;
    else ALUAMux <= RU1;

    if (ALUBSrc) ALUBMux <= RU2;
    else ALUBMux <= ImmExt;

    if (RUDataWrSrc == 2'b10) RUDataMux <= PcPlus4;
    else if (RUDataWrSrc == 2'b01) RUDataMux <= DataRd;
    else if (RUDataWrSrc == 2'b00) RUDataMux <= ALURes;
  end

endmodule

testbench/mono_tb.sv
module mono_tb;
  // Define clock parameters
  parameter CLK_PERIOD = 10;  // Clock period in time units
  parameter HALF_PERIOD = CLK_PERIOD / 2;  // Half clock period

  mono dut (.clk(clk));

  logic clk = 0;
  always #HALF_PERIOD clk = !clk;

  // Print content of submodules
  initial begin
    $dumpfile("dump.vcd");
    $dumpvars(0, mono_tb);

    for (int cycle = 0; cycle < 1000; cycle++) begin
      // Print the cycle number
      $display("Cycle %d:", cycle);

      // Loop through all registers and print their content
      for (int i = 0; i < 32; i++) begin
        if (i % 2 == 0)  // Print newline every 2 registers
          $write("\n");
        $write("x%d:%08h    ", i, dut.mregisterunit.registers[i]);
      end
      $write("\n");

      // Delay for one clock cycle
      #10;
    end
    $finish;
  end

endmodule

dump.vcd
$date
	Tue Apr 23 16:09:51 2024
$end
$version
	Icarus Verilog
$end
$timescale
	1s
$end
$scope module mono_tb $end
$var parameter 32 ! CLK_PERIOD $end
$var parameter 32 " HALF_PERIOD $end
$var reg 1 # clk $end
$scope module dut $end
$var wire 1 # clk $end
$var wire 32 $ inst [31:0] $end
$var wire 1 % RUWr $end
$var wire 2 & RUDataWrSrc [1:0] $end
$var wire 32 ' RU2 [31:0] $end
$var wire 32 ( RU1 [31:0] $end
$var wire 32 ) PcOutput [31:0] $end
$var wire 1 * NextPcSrc $end
$var wire 3 + ImmSrc [2:0] $end
$var wire 32 , ImmExt [31:0] $end
$var wire 32 - DataRd [31:0] $end
$var wire 1 . DMWr $end
$var wire 3 / DMCtrl [2:0] $end
$var wire 5 0 BrOp [4:0] $end
$var wire 32 1 ALURes [31:0] $end
$var wire 4 2 ALUOp [3:0] $end
$var wire 1 3 ALUBSrc $end
$var wire 1 4 ALUASrc $end
$var reg 32 5 ALUAMux [31:0] $end
$var reg 32 6 ALUBMux [31:0] $end
$var reg 32 7 BuPp4Mux [31:0] $end
$var reg 32 8 PcPlus4 [31:0] $end
$var reg 32 9 RUDataMux [31:0] $end
$scope module malu $end
$var wire 32 : A [31:0] $end
$var wire 32 ; B [31:0] $end
$var wire 4 < ALUOp [3:0] $end
$var reg 32 = S [31:0] $end
$upscope $end
$scope module mbranchunit $end
$var wire 32 > rs2 [31:0] $end
$var wire 32 ? rs1 [31:0] $end
$var wire 5 @ BrOp [4:0] $end
$var reg 1 * NextPcSrc $end
$upscope $end
$scope module mcontrolunit $end
$var wire 1 4 ALUASrc $end
$var wire 3 A DMCtrl [2:0] $end
$var wire 3 B Funct3 [2:0] $end
$var wire 7 C Funct7 [6:0] $end
$var wire 7 D OpCode [6:0] $end
$var wire 1 % RUWr $end
$var wire 2 E RUDataWrSrc [1:0] $end
$var wire 3 F ImmSrc [2:0] $end
$var wire 1 . DMWr $end
$var wire 5 G BrOp [4:0] $end
$var wire 1 3 ALUBSrc $end
$var reg 4 H ALUOp [3:0] $end
$upscope $end
$scope module mdatamemory $end
$var wire 32 I Address [31:0] $end
$var wire 3 J DMCtrl [2:0] $end
$var wire 1 . DMWr $end
$var wire 32 K DataWr [31:0] $end
$var reg 32 L DataRd [31:0] $end
$upscope $end
$scope module mimmunit $end
$var wire 25 M ImmInput [24:0] $end
$var wire 3 N ImmSrc [2:0] $end
$var reg 32 O ImmExt [31:0] $end
$upscope $end
$scope module minstmemory $end
$var wire 32 P instruction [31:0] $end
$var wire 32 Q address [31:0] $end
$upscope $end
$scope module mpc $end
$var wire 1 # clk $end
$var wire 32 R pc_input [31:0] $end
$var reg 32 S pc_output [31:0] $end
$upscope $end
$scope module mregisterunit $end
$var wire 1 % RuWr $end
$var wire 32 T RuWrData [31:0] $end
$var wire 1 # clk $end
$var wire 5 U rd [4:0] $end
$var wire 5 V rs1 [4:0] $end
$var wire 5 W rs2 [4:0] $end
$var wire 32 X ru1 [31:0] $end
$var wire 32 Y ru2 [31:0] $end
$var integer 32 Z i [31:0] $end
$var integer 32 [ j [31:0] $end
$upscope $end
$upscope $end
$scope begin $ivl_for_loop0 $end
$var integer 32 \ cycle [31:0] $end
$scope begin $ivl_for_loop1 $end
$var integer 32 ] i [31:0] $end
$upscope $end
$upscope $end
$upscope $end
$enddefinitions $end
$comment Show the parameter values. $end
$dumpall
b101 "
b1010 !
$end
#0
$dumpvars
b100000 ]
b0 \
b100001 [
b100001 Z
bx Y
bx X
bx W
bx V
bx U
bx T
bx S
b0 R
bx Q
bx P
bx O
bx N
bx M
bx L
bx K
bx J
bx I
bx H
bx G
bx F
bx E
bx D
bx C
bx B
bx A
bx @
bx ?
bx >
bx =
bx <
bx ;
bx :
bx 9
bx 8
b0 7
bx 6
bx 5
x4
x3
bx 2
bx 1
bx 0
bx /
x.
bx -
bx ,
bx +
x*
bx )
bx (
bx '
bx &
x%
bx $
0#
$end
#5
b11111111111111111111111111110000 9
b11111111111111111111111111110000 T
b11111111111111111111111111110000 1
b11111111111111111111111111110000 =
b11111111111111111111111111110000 I
0*
b11111111111111111111111111110000 6
b11111111111111111111111111110000 ;
b0 5
b0 :
b0 2
b0 <
b0 H
b100 7
b100 R
b100 8
b0 +
b0 F
b0 N
b0 0
b0 @
b0 G
04
b0 &
b0 E
b11111111111111111111111111110000 ,
b11111111111111111111111111110000 O
b0 '
b0 >
b0 K
b0 Y
b0 (
b0 ?
b0 X
1%
b1111111100000000000001000 M
b1000 U
b10000 W
b0 V
b1111111 C
b0 /
b0 A
b0 J
b0 B
13
0.
b10011 D
b11111111000000000000010000010011 $
b11111111000000000000010000010011 P
b0 )
b0 Q
b0 S
1#
#10
0#
b100000 ]
b1 \
#15
b11 9
b11 T
b1000 7
b1000 R
b11 1
b11 =
b11 I
b11 6
b11 ;
b1000 8
b11 ,
b11 O
b110000000001001 M
b1001 U
b11 W
b0 C
b1100000000010010010011 $
b1100000000010010010011 P
b100 )
b100 Q
b100 S
1#
#20
0#
b100000 ]
b10 \
#25
b1100 7
b1100 R
b10000 1
b10000 =
b10000 I
b1100 9
b1100 T
b1000 6
b1000 ;
b1000 5
b1000 :
b0 -
b0 L
b1100 8
b1110 0
b1110 @
b1110 G
b101 +
b101 F
b101 N
14
b10 &
b10 E
b1000 ,
b1000 O
b11 '
b11 >
b11 K
b11 Y
b11111111111111111111111111110000 (
b11111111111111111111111111110000 ?
b11111111111111111111111111110000 X
0%
b10010100011001000 M
b1000 U
b1001 W
b1000 V
b110 /
b110 A
b110 J
b110 B
b1100011 D
b100101000110010001100011 $
b100101000110010001100011 P
b1000 )
b1000 Q
b1000 S
1#
#30
0#
b100000 ]
b11 \
#35
b10000 7
b10000 R
b10 1
b10 =
b10 I
b10 9
b10 T
b10 6
b10 ;
0*
bx -
bx L
b0 5
b0 :
b10000 8
b0 0
b0 @
b0 G
b0 +
b0 F
b0 N
04
b0 &
b0 E
b10 ,
b10 O
b1000000000 '
b1000000000 >
b1000000000 K
b1000000000 Y
b0 (
b0 ?
b0 X
1%
b100101000001010 M
b1010 U
b10 W
b1010 V
b0 /
b0 A
b0 J
b0 B
b10011 D
b1001010000010100010011 $
b1001010000010100010011 P
b1100 )
b1100 Q
b1100 S
1#
#40
0#
b100000 ]
b100 \
#45
b11 9
b11 T
b10100 7
b10100 R
b11 1
b11 =
b11 I
b1 6
b1 ;
b10 5
b10 :
b10100 8
b1 ,
b1 O
b0 '
b0 >
b0 K
b0 Y
b10101000001010 M
b1 W
b101010000010100010011 $
b101010000010100010011 P
b10000 )
b10000 Q
b10000 S
b10 (
b10 ?
b10 X
1#
#50
0#
b100000 ]
b101 \
#55
b11000 7
b11000 R
bx 1
bx =
bx I
bx 6
bx ;
b0 -
b0 L
bx 5
bx :
b11000 8
bx 0
bx @
bx G
bx +
bx F
bx N
x4
bx &
bx E
b0 ,
b0 O
bx '
bx >
bx K
bx Y
x%
bx M
bx U
bx W
bx V
bx C
bx /
bx A
bx J
bx B
x3
x.
bx D
bx $
bx P
bx (
bx ?
bx X
b10100 )
b10100 Q
b10100 S
1#
#60
0#
b100000 ]
b110 \
#65
b11100 7
b11100 R
b11100 8
b11000 )
b11000 Q
b11000 S
1#
#70
0#
b100000 ]
b111 \
#75
b100000 7
b100000 R
b100000 8
b11100 )
b11100 Q
b11100 S
1#
#80
0#
b100000 ]
b1000 \
#85
b100100 7
b100100 R
b100100 8
b100000 )
b100000 Q
b100000 S
1#
#90
0#
b100000 ]
b1001 \
#95
b101000 7
b101000 R
b101000 8
b100100 )
b100100 Q
b100100 S
1#
#100
0#
b100000 ]
b1010 \
#105
b101100 7
b101100 R
b101100 8
b101000 )
b101000 Q
b101000 S
1#
#110
0#
b100000 ]
b1011 \
#115
b110000 7
b110000 R
b110000 8
b101100 )
b101100 Q
b101100 S
1#
#120
0#
b100000 ]
b1100 \
#125
b110100 7
b110100 R
b110100 8
b110000 )
b110000 Q
b110000 S
1#
#130
0#
b100000 ]
b1101 \
#135
b111000 7
b111000 R
b111000 8
b110100 )
b110100 Q
b110100 S
1#
#140
0#
b100000 ]
b1110 \
#145
b111100 7
b111100 R
b111100 8
b111000 )
b111000 Q
b111000 S
1#
#150
0#
b100000 ]
b1111 \
#155
b1000000 7
b1000000 R
b1000000 8
b111100 )
b111100 Q
b111100 S
1#
#160
0#
b100000 ]
b10000 \
#165
b1000100 7
b1000100 R
b1000100 8
b1000000 )
b1000000 Q
b1000000 S
1#
#170
0#
b100000 ]
b10001 \
#175
b1001000 7
b1001000 R
b1001000 8
b1000100 )
b1000100 Q
b1000100 S
1#
#180
0#
b100000 ]
b10010 \
#185
b1001100 7
b1001100 R
b1001100 8
b1001000 )
b1001000 Q
b1001000 S
1#
#190
0#
b100000 ]
b10011 \
#195
b1010000 7
b1010000 R
b1010000 8
b1001100 )
b1001100 Q
b1001100 S
1#
#200
0#
b100000 ]
b10100 \
#205
b1010100 7
b1010100 R
b1010100 8
b1010000 )
b1010000 Q
b1010000 S
1#
#210
0#
b100000 ]
b10101 \
#215
b1011000 7
b1011000 R
b1011000 8
b1010100 )
b1010100 Q
b1010100 S
1#
#220
0#
b100000 ]
b10110 \
#225
b1011100 7
b1011100 R
b1011100 8
b1011000 )
b1011000 Q
b1011000 S
1#
#230
0#
b100000 ]
b10111 \
#235
b1100000 7
b1100000 R
b1100000 8
b1011100 )
b1011100 Q
b1011100 S
1#
#240
0#
b100000 ]
b11000 \
#245
b1100100 7
b1100100 R
b1100100 8
b1100000 )
b1100000 Q
b1100000 S
1#
#250
0#
b100000 ]
b11001 \
#255
b1101000 7
b1101000 R
b1101000 8
b1100100 )
b1100100 Q
b1100100 S
1#
#260
0#
b100000 ]
b11010 \
#265
b1101100 7
b1101100 R
b1101100 8
b1101000 )
b1101000 Q
b1101000 S
1#
#270
0#
b100000 ]
b11011 \
#275
b1110000 7
b1110000 R
b1110000 8
b1101100 )
b1101100 Q
b1101100 S
1#
#280
0#
b100000 ]
b11100 \
#285
b1110100 7
b1110100 R
b1110100 8
b1110000 )
b1110000 Q
b1110000 S
1#
#290
0#
b100000 ]
b11101 \
#295
b1111000 7
b1111000 R
b1111000 8
b1110100 )
b1110100 Q
b1110100 S
1#
#300
0#
b100000 ]
b11110 \
#305
b1111100 7
b1111100 R
b1111100 8
b1111000 )
b1111000 Q
b1111000 S
1#
#310
0#
b100000 ]
b11111 \
#315
b10000000 7
b10000000 R
b10000000 8
b1111100 )
b1111100 Q
b1111100 S
1#
#320
0#
b100000 ]
b100000 \
#325
b10000100 7
b10000100 R
b10000100 8
b10000000 )
b10000000 Q
b10000000 S
1#
#330
0#
b100000 ]
b100001 \
#335
b10001000 7
b10001000 R
b10001000 8
b10000100 )
b10000100 Q
b10000100 S
1#
#340
0#
b100000 ]
b100010 \
#345
b10001100 7
b10001100 R
b10001100 8
b10001000 )
b10001000 Q
b10001000 S
1#
#350
0#
b100000 ]
b100011 \
#355
b10010000 7
b10010000 R
b10010000 8
b10001100 )
b10001100 Q
b10001100 S
1#
#360
0#
b100000 ]
b100100 \
#365
b10010100 7
b10010100 R
b10010100 8
b10010000 )
b10010000 Q
b10010000 S
1#
#370
0#
b100000 ]
b100101 \
#375
b10011000 7
b10011000 R
b10011000 8
b10010100 )
b10010100 Q
b10010100 S
1#
#380
0#
b100000 ]
b100110 \
#385
b10011100 7
b10011100 R
b10011100 8
b10011000 )
b10011000 Q
b10011000 S
1#
#390
0#
b100000 ]
b100111 \
#395
b10100000 7
b10100000 R
b10100000 8
b10011100 )
b10011100 Q
b10011100 S
1#
#400
0#
b100000 ]
b101000 \
#405
b10100100 7
b10100100 R
b10100100 8
b10100000 )
b10100000 Q
b10100000 S
1#
#410
0#
b100000 ]
b101001 \
#415
b10101000 7
b10101000 R
b10101000 8
b10100100 )
b10100100 Q
b10100100 S
1#
#420
0#
b100000 ]
b101010 \
#425
b10101100 7
b10101100 R
b10101100 8
b10101000 )
b10101000 Q
b10101000 S
1#
#430
0#
b100000 ]
b101011 \
#435
b10110000 7
b10110000 R
b10110000 8
b10101100 )
b10101100 Q
b10101100 S
1#
#440
0#
b100000 ]
b101100 \
#445
b10110100 7
b10110100 R
b10110100 8
b10110000 )
b10110000 Q
b10110000 S
1#
#450
0#
b100000 ]
b101101 \
#455
b10111000 7
b10111000 R
b10111000 8
b10110100 )
b10110100 Q
b10110100 S
1#
#460
0#
b100000 ]
b101110 \
#465
b10111100 7
b10111100 R
b10111100 8
b10111000 )
b10111000 Q
b10111000 S
1#
#470
0#
b100000 ]
b101111 \
#475
b11000000 7
b11000000 R
b11000000 8
b10111100 )
b10111100 Q
b10111100 S
1#
#480
0#
b100000 ]
b110000 \
#485
b11000100 7
b11000100 R
b11000100 8
b11000000 )
b11000000 Q
b11000000 S
1#
#490
0#
b100000 ]
b110001 \
#495
b11001000 7
b11001000 R
b11001000 8
b11000100 )
b11000100 Q
b11000100 S
1#
#500
0#
b100000 ]
b110010 \
#505
b11001100 7
b11001100 R
b11001100 8
b11001000 )
b11001000 Q
b11001000 S
1#
#510
0#
b100000 ]
b110011 \
#515
b11010000 7
b11010000 R
b11010000 8
b11001100 )
b11001100 Q
b11001100 S
1#
#520
0#
b100000 ]
b110100 \
#525
b11010100 7
b11010100 R
b11010100 8
b11010000 )
b11010000 Q
b11010000 S
1#
#530
0#
b100000 ]
b110101 \
#535
b11011000 7
b11011000 R
b11011000 8
b11010100 )
b11010100 Q
b11010100 S
1#
#540
0#
b100000 ]
b110110 \
#545
b11011100 7
b11011100 R
b11011100 8
b11011000 )
b11011000 Q
b11011000 S
1#
#550
0#
b100000 ]
b110111 \
#555
b11100000 7
b11100000 R
b11100000 8
b11011100 )
b11011100 Q
b11011100 S
1#
#560
0#
b100000 ]
b111000 \
#565
b11100100 7
b11100100 R
b11100100 8
b11100000 )
b11100000 Q
b11100000 S
1#
#570
0#
b100000 ]
b111001 \
#575
b11101000 7
b11101000 R
b11101000 8
b11100100 )
b11100100 Q
b11100100 S
1#
#580
0#
b100000 ]
b111010 \
#585
b11101100 7
b11101100 R
b11101100 8
b11101000 )
b11101000 Q
b11101000 S
1#
#590
0#
b100000 ]
b111011 \
#595
b11110000 7
b11110000 R
b11110000 8
b11101100 )
b11101100 Q
b11101100 S
1#
#600
0#
b100000 ]
b111100 \
#605
b11110100 7
b11110100 R
b11110100 8
b11110000 )
b11110000 Q
b11110000 S
1#
#610
0#
b100000 ]
b111101 \
#615
b11111000 7
b11111000 R
b11111000 8
b11110100 )
b11110100 Q
b11110100 S
1#
#620
0#
b100000 ]
b111110 \
#625
b11111100 7
b11111100 R
b11111100 8
b11111000 )
b11111000 Q
b11111000 S
1#
#630
0#
b100000 ]
b111111 \
#635
b100000000 7
b100000000 R
b100000000 8
b11111100 )
b11111100 Q
b11111100 S
1#
#640
0#
b100000 ]
b1000000 \
#645
b100000100 7
b100000100 R
b100000100 8
b100000000 )
b100000000 Q
b100000000 S
1#
#650
0#
b100000 ]
b1000001 \
#655
b100001000 7
b100001000 R
b100001000 8
b100000100 )
b100000100 Q
b100000100 S
1#
#660
0#
b100000 ]
b1000010 \
#665
b100001100 7
b100001100 R
b100001100 8
b100001000 )
b100001000 Q
b100001000 S
1#
#670
0#
b100000 ]
b1000011 \
#675
b100010000 7
b100010000 R
b100010000 8
b100001100 )
b100001100 Q
b100001100 S
1#
#680
0#
b100000 ]
b1000100 \
#685
b100010100 7
b100010100 R
b100010100 8
b100010000 )
b100010000 Q
b100010000 S
1#
#690
0#
b100000 ]
b1000101 \
#695
b100011000 7
b100011000 R
b100011000 8
b100010100 )
b100010100 Q
b100010100 S
1#
#700
0#
b100000 ]
b1000110 \
#705
b100011100 7
b100011100 R
b100011100 8
b100011000 )
b100011000 Q
b100011000 S
1#
#710
0#
b100000 ]
b1000111 \
#715
b100100000 7
b100100000 R
b100100000 8
b100011100 )
b100011100 Q
b100011100 S
1#
#720
0#
b100000 ]
b1001000 \
#725
b100100100 7
b100100100 R
b100100100 8
b100100000 )
b100100000 Q
b100100000 S
1#
#730
0#
b100000 ]
b1001001 \
#735
b100101000 7
b100101000 R
b100101000 8
b100100100 )
b100100100 Q
b100100100 S
1#
#740
0#
b100000 ]
b1001010 \
#745
b100101100 7
b100101100 R
b100101100 8
b100101000 )
b100101000 Q
b100101000 S
1#
#750
0#
b100000 ]
b1001011 \
#755
b100110000 7
b100110000 R
b100110000 8
b100101100 )
b100101100 Q
b100101100 S
1#
#760
0#
b100000 ]
b1001100 \
#765
b100110100 7
b100110100 R
b100110100 8
b100110000 )
b100110000 Q
b100110000 S
1#
#770
0#
b100000 ]
b1001101 \
#775
b100111000 7
b100111000 R
b100111000 8
b100110100 )
b100110100 Q
b100110100 S
1#
#780
0#
b100000 ]
b1001110 \
#785
b100111100 7
b100111100 R
b100111100 8
b100111000 )
b100111000 Q
b100111000 S
1#
#790
0#
b100000 ]
b1001111 \
#795
b101000000 7
b101000000 R
b101000000 8
b100111100 )
b100111100 Q
b100111100 S
1#
#800
0#
b100000 ]
b1010000 \
#805
b101000100 7
b101000100 R
b101000100 8
b101000000 )
b101000000 Q
b101000000 S
1#
#810
0#
b100000 ]
b1010001 \
#815
b101001000 7
b101001000 R
b101001000 8
b101000100 )
b101000100 Q
b101000100 S
1#
#820
0#
b100000 ]
b1010010 \
#825
b101001100 7
b101001100 R
b101001100 8
b101001000 )
b101001000 Q
b101001000 S
1#
#830
0#
b100000 ]
b1010011 \
#835
b101010000 7
b101010000 R
b101010000 8
b101001100 )
b101001100 Q
b101001100 S
1#
#840
0#
b100000 ]
b1010100 \
#845
b101010100 7
b101010100 R
b101010100 8
b101010000 )
b101010000 Q
b101010000 S
1#
#850
0#
b100000 ]
b1010101 \
#855
b101011000 7
b101011000 R
b101011000 8
b101010100 )
b101010100 Q
b101010100 S
1#
#860
0#
b100000 ]
b1010110 \
#865
b101011100 7
b101011100 R
b101011100 8
b101011000 )
b101011000 Q
b101011000 S
1#
#870
0#
b100000 ]
b1010111 \
#875
b101100000 7
b101100000 R
b101100000 8
b101011100 )
b101011100 Q
b101011100 S
1#
#880
0#
b100000 ]
b1011000 \
#885
b101100100 7
b101100100 R
b101100100 8
b101100000 )
b101100000 Q
b101100000 S
1#
#890
0#
b100000 ]
b1011001 \
#895
b101101000 7
b101101000 R
b101101000 8
b101100100 )
b101100100 Q
b101100100 S
1#
#900
0#
b100000 ]
b1011010 \
#905
b101101100 7
b101101100 R
b101101100 8
b101101000 )
b101101000 Q
b101101000 S
1#
#910
0#
b100000 ]
b1011011 \
#915
b101110000 7
b101110000 R
b101110000 8
b101101100 )
b101101100 Q
b101101100 S
1#
#920
0#
b100000 ]
b1011100 \
#925
b101110100 7
b101110100 R
b101110100 8
b101110000 )
b101110000 Q
b101110000 S
1#
#930
0#
b100000 ]
b1011101 \
#935
b101111000 7
b101111000 R
b101111000 8
b101110100 )
b101110100 Q
b101110100 S
1#
#940
0#
b100000 ]
b1011110 \
#945
b101111100 7
b101111100 R
b101111100 8
b101111000 )
b101111000 Q
b101111000 S
1#
#950
0#
b100000 ]
b1011111 \
#955
b110000000 7
b110000000 R
b110000000 8
b101111100 )
b101111100 Q
b101111100 S
1#
#960
0#
b100000 ]
b1100000 \
#965
b110000100 7
b110000100 R
b110000100 8
b110000000 )
b110000000 Q
b110000000 S
1#
#970
0#
b100000 ]
b1100001 \
#975
b110001000 7
b110001000 R
b110001000 8
b110000100 )
b110000100 Q
b110000100 S
1#
#980
0#
b100000 ]
b1100010 \
#985
b110001100 7
b110001100 R
b110001100 8
b110001000 )
b110001000 Q
b110001000 S
1#
#990
0#
b100000 ]
b1100011 \
#995
b110010000 7
b110010000 R
b110010000 8
b110001100 )
b110001100 Q
b110001100 S
1#
#1000
0#
b100000 ]
b1100100 \
#1005
b110010100 7
b110010100 R
b110010100 8
b110010000 )
b110010000 Q
b110010000 S
1#
#1010
0#
b100000 ]
b1100101 \
