datamemory.sv
module datamemory (
    input logic [31:0] Address,
    input logic [31:0] DataWr,
    input logic DMWr,
    input logic [2:0] DMCtrl,
    output logic [31:0] DataRd
);
  logic [7:0] memory[31:0];

  always @* begin
    case (DMCtrl)
      3'b000:  DataRd <= {{24{memory[Address][7]}}, memory[Address]};
      3'b001:  DataRd <= {{16{memory[Address+1][7]}}, memory[Address+1], memory[Address]};
      3'b010:  DataRd <= {memory[Address+3], memory[Address+2], memory[Address+1], memory[Address]};
      3'b100:  DataRd <= {{24{1'b0}}, memory[Address]};
      3'b101:  DataRd <= {{16{1'b0}}, memory[Address+1], memory[Address]};
      default: DataRd <= 0;
    endcase

    if (DMWr)
      if (DMCtrl == 3'b000) memory[Address] <= DataWr[7:0];
      else if (DMCtrl == 3'b001) begin
        memory[Address] <= DataWr[7:0];
        memory[Address+1] <= DataWr[15:8];
      end
      else if (DMCtrl == 3'b010) begin
        memory[Address] <= DataWr[7:0];
        memory[Address+1] <= DataWr[15:8];
        memory[Address+2] <= DataWr[23:16];
        memory[Address+3] <= DataWr[31:24];
      end
  end

endmodule

testbench/datamemory_tb.sv
module datamemory_tb;

  logic [31:0] Address;
  logic [31:0] DataWr;
  logic [2:0] DMCtrl;
  logic DMWr;
  logic [31:0] DataRd;

  datamemory dut (
      .Address(Address),
      .DataWr(DataWr),
      .DMCtrl(DMCtrl),
      .DMWr(DMWr),
      .DataRd(DataRd)
  );

  initial begin
    $dumpfile("dump.vcd");
    $dumpvars(0, datamemory_tb);

    //store at address 0 value 8 in byte format
    Address = 0;
    DataWr = 32'hf00000f8;
    DMCtrl = 3'b000;
    DMWr = 1;
    #10  //0

    //store at address 1 value -2 in half-word format
    Address = 1;
    DataWr = 32'h0000fffe;
    DMCtrl = 3'b001;
    DMWr   = 1;
    #10  //10

    //store at address 3 value 232 -1 in word format
    Address = 3;
    DataWr = 32'h80000001;
    DMCtrl = 3'b010;
    DMWr   = 1;
    #10  //20

    //read at address 10 unknown values
    Address = 10;
    DataWr = 32'h00000008;
    DMCtrl = 3'b000;
    DMWr   = 0;
    #10  //30

    //read at address 0 value 8 byte format
    Address = 0;
    DataWr = 32'h00000018;
    DMCtrl = 3'b000;
    DMWr   = 0;
    #10  //40

    // read at address 1 value -2 in half word format
    Address = 1;
    DataWr = 32'h0fff0ffe;
    DMCtrl = 3'b001;
    DMWr   = 0;
    #10  //50

    //read at address 3 value 232 -1 in word format
    Address = 3;
    DataWr = 32'h8010f001;
    DMCtrl = 3'b010;
    DMWr   = 0;
    #10  //60

    //read at address 1 value fffe in unsigned half-word format
    Address = 1;
    DataWr = 32'h0000ffff;
    DMCtrl = 3'b101;
    DMWr   = 0;
    #10  //70

    //read at address 0 value 8 in unsigned byte format
    Address = 0;
    DataWr = 32'h0000ffff;
    DMCtrl = 3'b100;
    DMWr   = 0;
    #10  //80


    $finish;

  end
endmodule

dump.vcd
$date
	Mon Apr 22 01:05:28 2024
$end
$version
	Icarus Verilog
$end
$timescale
	1s
$end
$scope module datamemory_tb $end
$var wire 32 ! DataRd [31:0] $end
$var reg 32 " Address [31:0] $end
$var reg 3 # DMCtrl [2:0] $end
$var reg 1 $ DMWr $end
$var reg 32 % DataWr [31:0] $end
$scope module dut $end
$var wire 32 & Address [31:0] $end
$var wire 3 ' DMCtrl [2:0] $end
$var wire 1 $ DMWr $end
$var wire 32 ( DataWr [31:0] $end
$var reg 32 ) DataRd [31:0] $end
$upscope $end
$upscope $end
$enddefinitions $end
$comment Show the parameter values. $end
$dumpall
$end
#0
$dumpvars
b11111111111111111111111111111000 )
b11110000000000000000000011111000 (
b0 '
b0 &
b11110000000000000000000011111000 %
1$
b0 #
b0 "
b11111111111111111111111111111000 !
$end
#10
b11111111111111111111111111111110 !
b11111111111111111111111111111110 )
b1 #
b1 '
b1111111111111110 %
b1111111111111110 (
b1 "
b1 &
#20
b10000000000000000000000000000001 !
b10000000000000000000000000000001 )
b10 #
b10 '
b10000000000000000000000000000001 %
b10000000000000000000000000000001 (
b11 "
b11 &
#30
bx !
bx )
0$
b0 #
b0 '
b1000 %
b1000 (
b1010 "
b1010 &
#40
b11111111111111111111111111111000 !
b11111111111111111111111111111000 )
b11000 %
b11000 (
b0 "
b0 &
#50
b11111111111111111111111111111110 !
b11111111111111111111111111111110 )
b1 #
b1 '
b1111111111110000111111111110 %
b1111111111110000111111111110 (
b1 "
b1 &
#60
b10000000000000000000000000000001 !
b10000000000000000000000000000001 )
b10 #
b10 '
b10000000000100001111000000000001 %
b10000000000100001111000000000001 (
b11 "
b11 &
#70
b1111111111111110 !
b1111111111111110 )
b101 #
b101 '
b1111111111111111 %
b1111111111111111 (
b1 "
b1 &
#80
b11111000 !
b11111000 )
b100 #
b100 '
b0 "
b0 &
