branchunit.sv
module branchunit (
    input logic [31:0] rs1,
    input logic [31:0] rs2,
    input logic [4:0] BrOp,
    output logic NextPcSrc
);

  always @* begin
    if (BrOp[4] == 1) NextPcSrc <= 1;
    else if (BrOp[4] == 0 && BrOp[3] == 0) NextPcSrc <= 0;
    else if (BrOp[4] == 0 && BrOp[3] == 1) if (BrOp[2:0] == 3'b000) NextPcSrc <= rs1 == rs2;
    if (BrOp[2:0] == 3'b001) NextPcSrc <= rs1 != rs2;
    if (BrOp[2:0] == 3'b100) NextPcSrc <= signed'(rs1) < signed'(rs2);
    if (BrOp[2:0] == 3'b101) NextPcSrc <= signed'(rs1) >= signed'(rs2);
    if (BrOp[2:0] == 3'b110) NextPcSrc <= rs1 < rs2;
    if (BrOp[2:0] == 3'b111) NextPcSrc <= rs1 >= rs2;
  end

endmodule

immunit.sv
module immunit (
    input  logic [24:0] ImmInput,
    input  logic [ 2:0] ImmSrc,
    output logic [31:0] ImmExt
);

  always @* begin
    case (ImmSrc)
      3'b000:  ImmExt = {{20{ImmInput[24]}}, ImmInput[24:13]};
      3'b001:  ImmExt = {{20{ImmInput[24]}}, ImmInput[24:18], ImmInput[4:0]};
      3'b101:  ImmExt = {{20{ImmInput[24]}}, ImmInput[0], ImmInput[23:18], ImmInput[4:1], 1'b0};
      3'b010:  ImmExt = {ImmInput[24:5], {12{1'b0}}};
      3'b110:  ImmExt = {{12{ImmInput[24]}}, ImmInput[12:5], ImmInput[13], ImmInput[23:14], 1'b0};
      default: ImmExt = 0;
    endcase
  end
endmodule

datamemory.sv
module datamemory (
    input logic [31:0] Address,
    input logic [31:0] DataWr,
    input logic DMWr,
    input logic [2:0] DMCtrl,
    output logic [31:0] DataRd
);
  logic [7:0] memory[1023:0];

  always @* begin
    case (DMCtrl)
      3'b000:  DataRd <= {{24{memory[Address][7]}}, memory[Address]};
      3'b001:  DataRd <= {{16{memory[Address+1][7]}}, memory[Address+1], memory[Address]};
      3'b010:  DataRd <= {memory[Address+3], memory[Address+2], memory[Address+1], memory[Address]};
      3'b100:  DataRd <= {{24{1'b0}}, memory[Address]};
      3'b101:  DataRd <= {{16{1'b0}}, memory[Address+1], memory[Address]};
      default: DataRd <= 0;
    endcase

    if (DMWr)
      #1
      if (DMCtrl == 3'b000) memory[Address] <= DataWr[7:0];
      else if (DMCtrl == 3'b001) begin
        memory[Address]   <= DataWr[7:0];
        memory[Address+1] <= DataWr[15:8];
      end else if (DMCtrl == 3'b010) begin
        memory[Address]   <= DataWr[7:0];
        memory[Address+1] <= DataWr[15:8];
        memory[Address+2] <= DataWr[23:16];
        memory[Address+3] <= DataWr[31:24];
      end
  end

endmodule

alu.sv
// Code your design here
module alu (
    input  logic [31:0] A,
    input  logic [31:0] B,
    input  logic [ 3:0] ALUOp,
    output logic [31:0] S
);
  always @(A, B, ALUOp) begin
    case (ALUOp)
      4'b0000: S = A + B;
      4'b1000: S = A - B;
      4'b0010: S = (signed'(A) < signed'(B));
      4'b0011: S = A < B;
      4'b0001: S = A << B[4:0];
      4'b0100: S = A ^ B;
      4'b0101: S = A >> B[4:0];
      4'b1101: S = signed'(A) >>> B[4:0];
      4'b0110: S = A | B;
      4'b0111: S = A & B;
      default: S = 0;
    endcase
  end
endmodule

registerunit.sv
module registerunit (
    input  logic        clk,       // Clock input
    input  logic [ 4:0] rs1,
    rs2,  // Inputs to select registers
    input  logic [ 4:0] rd,        // Input to select register for writing
    input  logic        RuWr,      // Write enable signal
    input  logic [31:0] RuWrData,  // Data to be written to the selected register
    output logic [31:0] ru1,
    ru2  // Outputs from selected registers
);

  // Define 32 registers each of 32 bits
  logic [31:0] registers[0:31];
  // Wire up ru1 and ru2 outputs
  assign ru1 = registers[rs1];
  assign ru2 = registers[rs2];

  integer i;
  integer j;
  initial begin
    for (i = 0; i <= 32; i = i + 1) for (j = 0; j <= 32; j = j + 1) registers[i][j] = 0;
    registers[2] = 32'd512;
  end

  always_ff @(negedge clk) begin
    if (RuWr && rd != 0) registers[rd] <= RuWrData;
  end

endmodule

controlunit.sv
module controlunit (
    input logic [6:0] OpCode,
    input logic [2:0] Funct3,
    input logic [6:0] Funct7,
    output logic RUWr,
    output logic [3:0] ALUOp,
    output logic [2:0] ImmSrc,
    output logic ALUASrc,
    output logic ALUBSrc,
    output logic DMWr,
    output logic [2:0] DMCtrl,
    output logic [4:0] BrOp,
    output logic [1:0] RUDataWrSrc
);
  assign RUWr = OpCode[5:2] != 4'b1000;

  always @* begin
    if (OpCode == 7'b0010011)
      if (Funct3 == 3'b001 || Funct3 == 3'b101)
        ALUOp <= {Funct7[5], Funct3[2], Funct3[1], Funct3[0]};
      else
        ALUOp <= {1'b0, Funct3};
    else if (OpCode == 7'b0110011) ALUOp <= {Funct7[5], Funct3[2], Funct3[1], Funct3[0]};
    else if ((OpCode == 7'b0110111) || (OpCode == 7'b0010111)) ALUOp <= 4'b0111;
    else ALUOp <= 4'b0000;
  end

  assign ImmSrc = {
    OpCode[3] + (OpCode[6] * (~OpCode[2])),
    OpCode[3] + ((~OpCode[6]) * OpCode[2]),
    (OpCode[5] * (~OpCode[2]))
  };

  assign ALUASrc = OpCode[6] && OpCode != 7'b1100111;
  assign ALUBSrc = OpCode != 7'b0110011;
  assign DMWr = OpCode == 7'b0100011;
  assign DMCtrl = Funct3;
  assign BrOp = {~OpCode[4] * OpCode[2], OpCode[6], Funct3[2], Funct3[1], Funct3[0]};
  assign RUDataWrSrc = {OpCode[6], ((~OpCode[6]) * (~OpCode[4]))};
endmodule

instmemory.sv
module instmemory (
    input  logic [31:0] address,
    output logic [31:0] instruction
);
  logic [7:0] memory[0:1023];
  assign instruction = { memory[address], memory[address+1], memory[address+2], memory[address+3] };

  initial begin
    $readmemh("../bubblesort_formatted.mem", memory);
  end
endmodule

pc.sv
module pc (
    input logic clk,
    input logic [31:0] pc_input,
    output logic [31:0] pc_output
);

  always_ff @(posedge clk) begin
    pc_output <= pc_input;
  end
endmodule

mono.sv
module mono (
    input logic clk
);
  logic [31:0] PcOutput;  // PC OUTPUT
  logic [31:0] PcPlus4;  // PC ADDED 4
  logic [31:0] BuPp4Mux;  // BRANCH UNIT and PC ADDED 4 mux
  logic [31:0] inst;  // INSTRUCTION MEMORY OUTPUT
  logic [31:0] RUDataMux;  // DATA MEMORY, ALU and PC ADDED 4 mux
  logic [31:0] RU1;  // REGISTER UNIT OUTPUT 1
  logic [31:0] RU2;  // REGISTER UNIT OUTPUT 2
  logic [31:0] ALUAMux;  // RU1 and PC mux
  logic [31:0] ALUBMux;  // RU2 and IMM GEN mux
  logic [31:0] ALURes;  // ALU OUTPUT
  logic [31:0] DataRd;  // DATA MEMORY OUTPUT
  logic [31:0] ImmExt;  // IMMEDIATE EXTENDED
  logic NextPcSrc;  // BRANCH UNIT OUTPUT

  /*    CONTROL UNIT    */
  logic RUWr;
  logic [3:0] ALUOp;
  logic [2:0] ImmSrc;
  logic ALUASrc;
  logic ALUBSrc;
  logic DMWr;
  logic [2:0] DMCtrl;
  logic [4:0] BrOp;
  logic [1:0] RUDataWrSrc;

  pc mpc (
      .clk(clk),
      .pc_input(BuPp4Mux),
      .pc_output(PcOutput)
  );

  instmemory minstmemory (
      .address(PcOutput),
      .instruction(inst)
  );

  controlunit mcontrolunit (
      .OpCode(inst[6:0]),
      .Funct3(inst[14:12]),
      .Funct7(inst[31:25]),
      .RUWr(RUWr),
      .ALUOp(ALUOp),
      .ImmSrc(ImmSrc),
      .ALUASrc(ALUASrc),
      .ALUBSrc(ALUBSrc),
      .DMWr(DMWr),
      .DMCtrl(DMCtrl),
      .BrOp(BrOp),
      .RUDataWrSrc(RUDataWrSrc)
  );

  registerunit mregisterunit (
      .clk(clk),
      .rs1(inst[19:15]),
      .rs2(inst[24:20]),
      .rd(inst[11:7]),
      .RuWr(RUWr),
      .RuWrData(RUDataMux),
      .ru1(RU1),
      .ru2(RU2)
  );

  alu malu (
      .A(ALUAMux),
      .B(ALUBMux),
      .ALUOp(ALUOp),
      .S(ALURes)
  );

  datamemory mdatamemory (
      .Address(ALURes),
      .DataWr(RU2),
      .DMWr(DMWr),
      .DMCtrl(DMCtrl),
      .DataRd(DataRd)
  );

  immunit mimmunit (
      .ImmInput(inst[31:7]),
      .ImmSrc  (ImmSrc),
      .ImmExt  (ImmExt)
  );

  branchunit mbranchunit (
      .rs1(RU2),
      .rs2(RU1),
      .BrOp(BrOp),
      .NextPcSrc(NextPcSrc)
  );

  always @* begin
    PcPlus4 <= PcOutput + 4;

    if (NextPcSrc) BuPp4Mux <= ALURes;
    else BuPp4Mux <= PcPlus4;

    if (ALUASrc) ALUAMux <= PcOutput;
    else ALUAMux <= RU1;

    if (ALUBSrc) ALUBMux <= RU2;
    else ALUBMux <= ImmExt;

    if (RUDataWrSrc == 2'b10) RUDataMux <= PcPlus4;
    else if (RUDataWrSrc == 2'b01) RUDataMux <= DataRd;
    else if (RUDataWrSrc == 2'b00) RUDataMux <= ALURes;
  end

endmodule

testbench/mono_tb.sv
module mono_tb;
  // Define clock parameters
  parameter CLK_PERIOD = 10;  // Clock period in time units
  parameter HALF_PERIOD = CLK_PERIOD / 2;  // Half clock period

  mono dut (.clk(clk));

  logic clk = 0;
  always #HALF_PERIOD clk = !clk;

  // Print content of submodules
  initial begin
    $dumpfile("dump.vcd");
    $dumpvars(0, mono_tb);

    for (int cycle = 0; cycle < 1000; cycle++) begin
      // Print the cycle number
      $display("Cycle %d:", cycle);

      // Loop through all registers and print their content
      for (int i = 0; i < 32; i++) begin
        if (i % 2 == 0)  // Print newline every 2 registers
          $write("\n");
        $write("x%d:%08h    ", i, dut.mregisterunit.registers[i]);
      end
      $write("\n");

      // Delay for one clock cycle
      #10;
    end
    $finish;
  end

endmodule

testbench/dump.vcd
$date
	Mon Apr 29 14:00:26 2024
$end
$version
	Icarus Verilog
$end
$timescale
	1s
$end
$scope module mono_tb $end
$var parameter 32 ! CLK_PERIOD $end
$var parameter 32 " HALF_PERIOD $end
$var reg 1 # clk $end
$scope module dut $end
$var wire 1 # clk $end
$var wire 32 $ inst [31:0] $end
$var wire 1 % RUWr $end
$var wire 2 & RUDataWrSrc [1:0] $end
$var wire 32 ' RU2 [31:0] $end
$var wire 32 ( RU1 [31:0] $end
$var wire 32 ) PcOutput [31:0] $end
$var wire 1 * NextPcSrc $end
$var wire 3 + ImmSrc [2:0] $end
$var wire 32 , ImmExt [31:0] $end
$var wire 32 - DataRd [31:0] $end
$var wire 1 . DMWr $end
$var wire 3 / DMCtrl [2:0] $end
$var wire 5 0 BrOp [4:0] $end
$var wire 32 1 ALURes [31:0] $end
$var wire 4 2 ALUOp [3:0] $end
$var wire 1 3 ALUBSrc $end
$var wire 1 4 ALUASrc $end
$var reg 32 5 ALUAMux [31:0] $end
$var reg 32 6 ALUBMux [31:0] $end
$var reg 32 7 BuPp4Mux [31:0] $end
$var reg 32 8 PcPlus4 [31:0] $end
$var reg 32 9 RUDataMux [31:0] $end
$scope module malu $end
$var wire 32 : A [31:0] $end
$var wire 32 ; B [31:0] $end
$var wire 4 < ALUOp [3:0] $end
$var reg 32 = S [31:0] $end
$upscope $end
$scope module mbranchunit $end
$var wire 32 > rs2 [31:0] $end
$var wire 32 ? rs1 [31:0] $end
$var wire 5 @ BrOp [4:0] $end
$var reg 1 * NextPcSrc $end
$upscope $end
$scope module mcontrolunit $end
$var wire 1 4 ALUASrc $end
$var wire 3 A DMCtrl [2:0] $end
$var wire 3 B Funct3 [2:0] $end
$var wire 7 C Funct7 [6:0] $end
$var wire 7 D OpCode [6:0] $end
$var wire 1 % RUWr $end
$var wire 2 E RUDataWrSrc [1:0] $end
$var wire 3 F ImmSrc [2:0] $end
$var wire 1 . DMWr $end
$var wire 5 G BrOp [4:0] $end
$var wire 1 3 ALUBSrc $end
$var reg 4 H ALUOp [3:0] $end
$upscope $end
$scope module mdatamemory $end
$var wire 32 I Address [31:0] $end
$var wire 3 J DMCtrl [2:0] $end
$var wire 1 . DMWr $end
$var wire 32 K DataWr [31:0] $end
$var reg 32 L DataRd [31:0] $end
$upscope $end
$scope module mimmunit $end
$var wire 25 M ImmInput [24:0] $end
$var wire 3 N ImmSrc [2:0] $end
$var reg 32 O ImmExt [31:0] $end
$upscope $end
$scope module minstmemory $end
$var wire 32 P instruction [31:0] $end
$var wire 32 Q address [31:0] $end
$upscope $end
$scope module mpc $end
$var wire 1 # clk $end
$var wire 32 R pc_input [31:0] $end
$var reg 32 S pc_output [31:0] $end
$upscope $end
$scope module mregisterunit $end
$var wire 1 % RuWr $end
$var wire 32 T RuWrData [31:0] $end
$var wire 1 # clk $end
$var wire 5 U rd [4:0] $end
$var wire 5 V rs1 [4:0] $end
$var wire 5 W rs2 [4:0] $end
$var wire 32 X ru1 [31:0] $end
$var wire 32 Y ru2 [31:0] $end
$var integer 32 Z i [31:0] $end
$var integer 32 [ j [31:0] $end
$upscope $end
$upscope $end
$scope begin $ivl_for_loop0 $end
$var integer 32 \ cycle [31:0] $end
$scope begin $ivl_for_loop1 $end
$var integer 32 ] i [31:0] $end
$upscope $end
$upscope $end
$upscope $end
$enddefinitions $end
$comment Show the parameter values. $end
$dumpall
b101 "
b1010 !
$end
#0
$dumpvars
b100000 ]
b0 \
b100001 [
b100001 Z
bx Y
bx X
bx W
bx V
bx U
bx T
bx S
b0 R
bx Q
bx P
bx O
bx N
bx M
bx L
bx K
bx J
bx I
bx H
bx G
bx F
bx E
bx D
bx C
bx B
bx A
bx @
bx ?
bx >
bx =
bx <
bx ;
bx :
bx 9
bx 8
b0 7
bx 6
bx 5
x4
x3
bx 2
bx 1
bx 0
bx /
x.
bx -
bx ,
bx +
x*
bx )
bx (
bx '
bx &
x%
bx $
0#
$end
#5
b1101000 9
b1101000 T
b1101000 1
b1101000 =
b1101000 I
0*
b1101000 6
b1101000 ;
b0 5
b0 :
b0 2
b0 <
b0 H
b100 7
b100 R
b100 8
b0 +
b0 F
b0 N
b0 0
b0 @
b0 G
04
b0 &
b0 E
b1101000 ,
b1101000 O
b0 '
b0 >
b0 K
b0 Y
b0 (
b0 ?
b0 X
1%
b11010000000000001010 M
b1010 U
b1000 W
b0 V
b11 C
b0 /
b0 A
b0 J
b0 B
13
0.
b10011 D
b110100000000000010100010011 $
b110100000000000010100010011 P
b0 )
b0 Q
b0 S
1#
#10
0#
b100000 ]
b1 \
#15
b101 9
b101 T
b1000 7
b1000 R
b101 1
b101 =
b101 I
b101 6
b101 ;
b1000 8
b101 ,
b101 O
b1010000000001011 M
b1011 U
b101 W
b0 C
b10100000000010110010011 $
b10100000000010110010011 P
b100 )
b100 Q
b100 S
1#
#20
0#
b100000 ]
b10 \
#25
b111 9
b111 T
b1100 7
b1100 R
b111 1
b111 =
b111 I
b111 6
b111 ;
b1100 8
b111 ,
b111 O
b1110000000000101 M
b101 U
b111 W
b11100000000001010010011 $
b11100000000001010010011 P
b1000 )
b1000 Q
b1000 S
1#
#30
0#
b100000 ]
b11 \
#35
b10000 9
b10000 T
b10000 7
b10000 R
b10000 1
b10000 =
b10000 I
b10000 6
b10000 ;
b10000 8
b10000 ,
b10000 O
b100000000000000110 M
b110 U
b10000 W
b1000000000000001100010011 $
b1000000000000001100010011 P
b1100 )
b1100 Q
b1100 S
1#
#40
0#
b100000 ]
b100 \
#45
b11 9
b11 T
b10100 7
b10100 R
b11 1
b11 =
b11 I
b11 6
b11 ;
b10100 8
b11 ,
b11 O
b110000000000111 M
b111 U
b11 W
b1100000000001110010011 $
b1100000000001110010011 P
b10000 )
b10000 Q
b10000 S
1#
#50
0#
b100000 ]
b101 \
#55
b0 9
b0 T
b11000 7
b11000 R
b0 1
b0 =
b0 I
b0 6
b0 ;
b11000 8
b0 ,
b0 O
b11100 M
b11100 U
b0 W
b111000010011 $
b111000010011 P
b10100 )
b10100 Q
b10100 S
1#
#60
0#
b100000 ]
b110 \
#65
b100001 9
b100001 T
b11100 7
b11100 R
b100001 1
b100001 =
b100001 I
b100001 6
b100001 ;
b11100 8
b100001 ,
b100001 O
b1000010000000011101 M
b11101 U
b1 W
b1 C
b10000100000000111010010011 $
b10000100000000111010010011 P
b11000 )
b11000 Q
b11000 S
1#
#70
0#
b100000 ]
b111 \
#75
b100000 7
b100000 R
b1101000 1
b1101000 =
b1101000 I
bx 9
bx T
b0 6
b0 ;
b1101000 5
b1101000 :
b100000 8
b10 0
b10 @
b10 G
b1 &
b1 E
b1 +
b1 F
b1 N
b0 ,
b0 O
b111 '
b111 >
b111 K
b111 Y
b1101000 (
b1101000 ?
b1101000 X
0%
b1010101001000000 M
b0 U
b101 W
b1010 V
b0 C
b10 /
b10 A
b10 J
b10 B
1.
b100011 D
b10101010010000000100011 $
b10101010010000000100011 P
b11100 )
b11100 Q
b11100 S
1#
#76
b111 9
b111 T
b111 -
b111 L
#80
0#
b100000 ]
b1000 \
#85
b100100 7
b100100 R
b1101100 1
b1101100 =
b1101100 I
b100 6
b100 ;
b100100 8
b100 ,
b100 O
b10000 '
b10000 >
b10000 K
b10000 Y
b1100101001000100 M
b100 U
b110 W
b11001010010001000100011 $
b11001010010001000100011 P
b100000 )
b100000 Q
b100000 S
1#
#86
b10000 9
b10000 T
b10000 -
b10000 L
#90
0#
b100000 ]
b1001 \
#95
b101000 7
b101000 R
b1110000 1
b1110000 =
b1110000 I
b1000 6
b1000 ;
b101000 8
b1000 ,
b1000 O
b11 '
b11 >
b11 K
b11 Y
b1110101001001000 M
b1000 U
b111 W
b11101010010010000100011 $
b11101010010010000100011 P
b100100 )
b100100 Q
b100100 S
1#
#96
b11 9
b11 T
b11 -
b11 L
#100
0#
b100000 ]
b1010 \
#105
b101100 7
b101100 R
b1110100 1
b1110100 =
b1110100 I
b1100 6
b1100 ;
b101100 8
b1100 ,
b1100 O
b0 '
b0 >
b0 K
b0 Y
b111000101001001100 M
b1100 U
b11100 W
b1110001010010011000100011 $
b1110001010010011000100011 P
b101000 )
b101000 Q
b101000 S
1#
#106
b0 9
b0 T
b0 -
b0 L
#110
0#
b100000 ]
b1011 \
#115
b110000 7
b110000 R
b1111000 1
b1111000 =
b1111000 I
b10000 6
b10000 ;
b110000 8
b10000 ,
b10000 O
b100001 '
b100001 >
b100001 K
b100001 Y
b111010101001010000 M
b10000 U
b11101 W
b1110101010010100000100011 $
b1110101010010100000100011 P
b101100 )
b101100 Q
b101100 S
1#
#116
b100001 9
b100001 T
b100001 -
b100001 L
#120
0#
b100000 ]
b1100 \
#125
bx -
bx L
b111000 7
b111000 R
b111000 1
b111000 =
b111000 I
1*
b110100 9
b110100 T
b1000 6
b1000 ;
b110000 5
b110000 :
b110100 8
b11000 0
b11000 @
b11000 G
b110 +
b110 F
b110 N
14
b10 &
b10 E
b1000 ,
b1000 O
b0 '
b0 >
b0 K
b0 Y
b0 (
b0 ?
b0 X
1%
b10000000000000001 M
b1 U
b1000 W
b0 V
b0 /
b0 A
b0 J
b0 B
0.
b1101111 D
b100000000000000011101111 $
b100000000000000011101111 P
b110000 )
b110000 Q
b110000 S
1#
#130
0#
b100000 ]
b1101 \
#135
b111100 7
b111100 R
b111101100 1
b111101100 =
b111101100 I
0*
b111101100 9
b111101100 T
b11111111111111111111111111101100 6
b11111111111111111111111111101100 ;
b1000000000 5
b1000000000 :
b111100 8
b0 0
b0 @
b0 G
b0 +
b0 F
b0 N
04
b0 &
b0 E
b11111111111111111111111111101100 ,
b11111111111111111111111111101100 O
b1000000000 (
b1000000000 ?
b1000000000 X
b1111111011000001000000010 M
b10 U
b1100 W
b10 V
b1111111 C
b10011 D
b11111110110000010000000100010011 $
b11111110110000010000000100010011 P
b111000 )
b111000 Q
b111000 S
1#
#140
0#
b100000 ]
b1110 \
#145
b1000000 7
b1000000 R
bx 9
bx T
b0 6
b0 ;
b111101100 5
b111101100 :
b1000000 8
b10 0
b10 @
b10 G
b1 &
b1 E
b1 +
b1 F
b1 N
b0 ,
b0 O
0%
b10000001001000000 M
b0 U
b1000 W
b0 C
b10 /
b10 A
b10 J
b10 B
1.
b100011 D
b100000010010000000100011 $
b100000010010000000100011 P
b111100 )
b111100 Q
b111100 S
b111101100 (
b111101100 ?
b111101100 X
1#
#146
b0 9
b0 T
b0 -
b0 L
#150
0#
b100000 ]
b1111 \
#155
bx 9
bx T
bx -
bx L
b1000100 7
b1000100 R
b111110000 1
b111110000 =
b111110000 I
b100 6
b100 ;
b1000100 8
b100 ,
b100 O
b10010001001000100 M
b100 U
b1001 W
b100100010010001000100011 $
b100100010010001000100011 P
b1000000 )
b1000000 Q
b1000000 S
1#
#156
b0 9
b0 T
b0 -
b0 L
#160
0#
b100000 ]
b10000 \
#165
bx 9
bx T
bx -
bx L
b1001000 7
b1001000 R
b111110100 1
b111110100 =
b111110100 I
b1000 6
b1000 ;
b1001000 8
b1000 ,
b1000 O
b100100001001001000 M
b1000 U
b10010 W
b1001000010010010000100011 $
b1001000010010010000100011 P
b1000100 )
b1000100 Q
b1000100 S
1#
#166
b0 9
b0 T
b0 -
b0 L
#170
0#
b100000 ]
b10001 \
#175
bx 9
bx T
bx -
bx L
b1001100 7
b1001100 R
b111111000 1
b111111000 =
b111111000 I
b1100 6
b1100 ;
b1001100 8
b1100 ,
b1100 O
b100110001001001100 M
b1100 U
b10011 W
b1001100010010011000100011 $
b1001100010010011000100011 P
b1001000 )
b1001000 Q
b1001000 S
1#
#176
b0 9
b0 T
b0 -
b0 L
#180
0#
b100000 ]
b10010 \
#185
bx 9
bx T
bx -
bx L
b1010000 7
b1010000 R
b111111100 1
b111111100 =
b111111100 I
b10000 6
b10000 ;
b1010000 8
b10000 ,
b10000 O
b101000001001010000 M
b10000 U
b10100 W
b1010000010010100000100011 $
b1010000010010100000100011 P
b1001100 )
b1001100 Q
b1001100 S
1#
#186
b0 9
b0 T
b0 -
b0 L
#190
0#
b100000 ]
b10011 \
#195
bx 9
bx T
bx -
bx L
b1010100 7
b1010100 R
b1000000000 1
b1000000000 =
b1000000000 I
b10100 6
b10100 ;
b1010100 8
b10100 ,
b10100 O
b101010001001010100 M
b10100 U
b10101 W
b1010100010010101000100011 $
b1010100010010101000100011 P
b1010000 )
b1010000 Q
b1010000 S
1#
#196
b0 9
b0 T
b0 -
b0 L
#200
0#
b100000 ]
b10100 \
#205
b111 -
b111 L
b1011000 7
b1011000 R
b1101000 1
b1101000 =
b1101000 I
b1101000 9
b1101000 T
b0 6
b0 ;
b1101000 5
b1101000 :
b1011000 8
b0 0
b0 @
b0 G
b0 &
b0 E
b0 +
b0 F
b0 N
b0 ,
b0 O
b1101000 (
b1101000 ?
b1101000 X
1%
b101000001000 M
b1000 U
b0 W
b1010 V
b0 /
b0 A
b0 J
b0 B
0.
b10011 D
b1010000010000010011 $
b1010000010000010011 P
b1010100 )
b1010100 Q
b1010100 S
1#
#210
0#
b100000 ]
b10101 \
#215
bx -
bx L
b101 9
b101 T
b1011100 7
b1011100 R
b101 1
b101 =
b101 I
b101 5
b101 :
b1011100 8
b101 (
b101 ?
b101 X
b101100001001 M
b1001 U
b1011 V
b1011000010010010011 $
b1011000010010010011 P
b1011000 )
b1011000 Q
b1011000 S
1#
#220
0#
b100000 ]
b10110 \
#225
b1100000 7
b1100000 R
b1100000 8
b100100010010 M
b10010 U
b1001 V
b1001000100100010011 $
b1001000100100010011 P
b1011100 )
b1011100 Q
b1011100 S
1#
#230
0#
b100000 ]
b10111 \
#235
b0 9
b0 T
b1100100 7
b1100100 R
b0 1
b0 =
b0 I
b0 5
b0 :
b1100100 8
b0 (
b0 ?
b0 X
b10011 M
b10011 U
b0 V
b100110010011 $
b100110010011 P
b1100000 )
b1100000 Q
b1100000 S
1#
#240
0#
b100000 ]
b11000 \
#245
b1101000 7
b1101000 R
b10101000 1
b10101000 =
b10101000 I
b1101000 9
b1101000 T
b1000100 6
b1000100 ;
b1100100 5
b1100100 :
b0xxxxxxxx -
b0xxxxxxxx L
b1101000 8
b1100 0
b1100 @
b1100 G
b101 +
b101 F
b101 N
14
b10 &
b10 E
b1000100 ,
b1000100 O
b101 (
b101 ?
b101 X
0%
b10000001001010000100 M
b100 U
b10010 V
b10 C
b100 /
b100 A
b100 J
b100 B
b1100011 D
b100000010010100001001100011 $
b100000010010100001001100011 P
b1100100 )
b1100100 Q
b1100100 S
1#
#250
0#
b100000 ]
b11001 \
#255
b1101100 7
b1101100 R
b0 1
b0 =
b0 I
b0 9
b0 T
b0 6
b0 ;
bx -
bx L
b0 5
b0 :
b1101100 8
b0 0
b0 @
b0 G
b0 +
b0 F
b0 N
04
b0 &
b0 E
b0 ,
b0 O
b0 (
b0 ?
b0 X
1%
b10011 M
b10011 U
b0 V
b0 C
b0 /
b0 A
b0 J
b0 B
b10011 D
b100110010011 $
b100110010011 P
b1101000 )
b1101000 Q
b1101000 S
1#
#260
0#
b100000 ]
b11010 \
#265
b100 9
b100 T
b1110000 7
b1110000 R
b100 1
b100 =
b100 I
b11111111111111111111111111111111 6
b11111111111111111111111111111111 ;
b101 5
b101 :
b1110000 8
b11111111111111111111111111111111 ,
b11111111111111111111111111111111 O
b101 (
b101 ?
b101 X
b1111111111111001000000101 M
b101 U
b11111 W
b10010 V
b1111111 C
b11111111111110010000001010010011 $
b11111111111110010000001010010011 P
b1101100 )
b1101100 Q
b1101100 S
1#
#270
0#
b100000 ]
b11011 \
#275
b1110100 7
b1110100 R
b10100000 1
b10100000 =
b10100000 I
b1110100 9
b1110100 T
b110000 6
b110000 ;
b1110000 5
b1110000 :
b0xxxxxxxxxxxxxxxx -
b0xxxxxxxxxxxxxxxx L
b1110100 8
b1101 0
b1101 @
b1101 G
b101 +
b101 F
b101 N
14
b10 &
b10 E
b110000 ,
b110000 O
b100 '
b100 >
b100 K
b100 Y
b0 (
b0 ?
b0 X
0%
b1001011001110110000 M
b10000 U
b101 W
b10011 V
b1 C
b101 /
b101 A
b101 J
b101 B
b1100011 D
b10010110011101100001100011 $
b10010110011101100001100011 P
b1110000 )
b1110000 Q
b1110000 S
1#
#280
0#
b100000 ]
b11100 \
#285
b1111000 7
b1111000 R
b0 1
b0 =
b0 I
b0 9
b0 T
b0 6
b0 ;
0*
bx -
bx L
b0 5
b0 :
b1111000 8
b0 0
b0 @
b0 G
b0 +
b0 F
b0 N
04
b0 &
b0 E
b0 ,
b0 O
b0 '
b0 >
b0 K
b0 Y
1%
b1001100000110 M
b110 U
b0 W
b0 C
b0 /
b0 A
b0 J
b0 B
b10011 D
b10011000001100010011 $
b10011000001100010011 P
b1110100 )
b1110100 Q
b1110100 S
1#
#290
0#
b100000 ]
b11101 \
#295
b1111100 7
b1111100 R
b10 6
b10 ;
b1 2
b1 <
b1 H
b1111100 8
b1 0
b1 @
b1 G
b10 ,
b10 O
b111101100 '
b111101100 >
b111101100 K
b111101100 Y
b100011000100110 M
b10 W
b110 V
b1 /
b1 A
b1 J
b1 B
b1000110001001100010011 $
b1000110001001100010011 P
b1111000 )
b1111000 Q
b1111000 S
1#
#300
0#
b100000 ]
b11110 \
#305
b111 -
b111 L
b1101000 9
b1101000 T
b10000000 7
b10000000 R
b1101000 1
b1101000 =
b1101000 I
b1101000 5
b1101000 :
b0 2
b0 <
b0 H
b0 6
b0 ;
b10000000 8
b0 0
b0 @
b0 G
b1 +
b1 F
b1 N
b110 ,
b110 O
b0 '
b0 >
b0 K
b0 Y
b1101000 (
b1101000 ?
b1101000 X
b1100100000000110 M
b110 W
b1000 V
b0 /
b0 A
b0 J
b0 B
03
b110011 D
b11001000000001100110011 $
b11001000000001100110011 P
b1111100 )
b1111100 Q
b1111100 S
1#
#310
0#
b100000 ]
b11111 \
#315
b10000 -
b10000 L
b1101100 9
b1101100 T
b10000100 7
b10000100 R
b1101100 1
b1101100 =
b1101100 I
b100 6
b100 ;
b10000100 8
b0 +
b0 F
b0 N
b100 ,
b100 O
b1000011000000111 M
b111 U
b100 W
b110 V
13
b10011 D
b10000110000001110010011 $
b10000110000001110010011 P
b0 '
b0 >
b0 K
b0 Y
b10000000 )
b10000000 Q
b10000000 S
1#
#320
0#
b100000 ]
b100000 \
#325
b111 -
b111 L
b10001000 7
b10001000 R
b1101000 1
b1101000 =
b1101000 I
b111 9
b111 T
b0 6
b0 ;
b10001000 8
b10 0
b10 @
b10 G
b1 &
b1 E
b0 ,
b0 O
b11001010100 M
b10100 U
b0 W
b10 /
b10 A
b10 J
b10 B
b11 D
b110010101000000011 $
b110010101000000011 P
b10000100 )
b10000100 Q
b10000100 S
1#
#330
0#
b100000 ]
b100001 \
#335
b10000 9
b10000 T
b10000 -
b10000 L
b10001100 7
b10001100 R
b1101100 1
b1101100 =
b1101100 I
b1101100 5
b1101100 :
b10001100 8
b1101100 (
b1101100 ?
b1101100 X
b11101010101 M
b10101 U
b111 V
b111010101010000011 $
b111010101010000011 P
b10001000 )
b10001000 Q
b10001000 S
1#
#340
0#
b100000 ]
b100010 \
#345
b0xxxxxxxxxxxxxxxx -
b0xxxxxxxxxxxxxxxx L
b10011000 7
b10011000 R
b10011000 1
b10011000 =
b10011000 I
1*
b10010000 9
b10010000 T
b1100 6
b1100 ;
b10001100 5
b10001100 :
b10010000 8
b1101 0
b1101 @
b1101 G
b101 +
b101 F
b101 N
14
b10 &
b10 E
b1100 ,
b1100 O
b111 '
b111 >
b111 K
b111 Y
b10000 (
b10000 ?
b10000 X
0%
b101001010110101100 M
b1100 U
b10100 W
b10101 V
b101 /
b101 A
b101 J
b101 B
b1100011 D
b1010010101101011001100011 $
b1010010101101011001100011 P
b10001100 )
b10001100 Q
b10001100 S
1#
#350
0#
b100000 ]
b100011 \
